varprox/__init__.py
varprox/_minimize.py
varprox/_parameters.py
varprox/models/__init__.py
varprox/models/model_mfbm.py
varprox-1.0.7.dist-info/licenses/AUTHORS.rst
varprox-1.0.7.dist-info/licenses/LICENSE.rst
varprox-1.0.7.dist-info/METADATA
varprox-1.0.7.dist-info/WHEEL
varprox-1.0.7.dist-info/entry_points.txt
varprox-1.0.7.dist-info/top_level.txt
varprox-1.0.7.dist-info/RECORD
