Metadata-Version: 2.4
Name: varprox
Version: 1.0.7
Summary: Optimization algorithms for solving penalized non-linear least squares problems
Home-page: https://github.com/Varprox/varprox
Author: Arthur Marmin and Frederic Richard
Author-email: frederic.richard@univ-amu.fr
License: GPLv3
Project-URL: Documentation, https://varprox.github.io/varprox/
Project-URL: Source, https://github.com/Varprox/varprox/
Project-URL: Tracker, https://github.com/Varprox/varprox/issues
Keywords: separable non linear least squares,data fitting,optimization
Platform: Linux
Platform: MacOSX
Platform: Windows
Classifier: License :: OSI Approved :: GNU General Public License v3 (GPLv3)
Classifier: Development Status :: 5 - Production/Stable
Classifier: Intended Audience :: Science/Research
Classifier: Intended Audience :: End Users/Desktop
Classifier: Intended Audience :: Developers
Classifier: Natural Language :: English
Classifier: Operating System :: OS Independent
Classifier: Programming Language :: Python :: 3.11
Classifier: Topic :: Scientific/Engineering :: Mathematics
License-File: LICENSE.rst
License-File: AUTHORS.rst
Requires-Dist: numpy>=1.16.1
Requires-Dist: scipy>=1.16.1
Provides-Extra: examples
Requires-Dist: pyafbf>=0.2.9; extra == "examples"
Requires-Dist: matplotlib>=3.10.0; extra == "examples"
Dynamic: author
Dynamic: author-email
Dynamic: classifier
Dynamic: description
Dynamic: home-page
Dynamic: keywords
Dynamic: license
Dynamic: license-file
Dynamic: platform
Dynamic: project-url
Dynamic: provides-extra
Dynamic: requires-dist
Dynamic: summary
